library/Abs.py
library/NumThe.py
library/OtherNumThe.py
NumThe-1.1.dist-info/METADATA
NumThe-1.1.dist-info/WHEEL
NumThe-1.1.dist-info/top_level.txt
NumThe-1.1.dist-info/RECORD
