Metadata-Version: 2.1
Name: NumThe
Version: 1.1
Summary: some common Number Theory
Home-page: UNKNOWN
Author: 夜黎
Author-email: z2544427399@163.com
License: UNKNOWN
Platform: UNKNOWN
Requires-Dist: itertools
Requires-Dist: abc
